MANIFEST.in
README.md
requirements.txt
setup.py
OPCDataTransfer/DataTransfer.py
OPCDataTransfer/__init__.py
OPCDataTransfer.egg-info/PKG-INFO
OPCDataTransfer.egg-info/SOURCES.txt
OPCDataTransfer.egg-info/dependency_links.txt
OPCDataTransfer.egg-info/entry_points.txt
OPCDataTransfer.egg-info/requires.txt
OPCDataTransfer.egg-info/top_level.txt
OPCDataTransfer/Data/logs.log
OPCDataTransfer/Data/opc_settings.xml
OPCDataTransfer/Data/run_settings_sample.ini
OPCDataTransfer/Data/tags_settings_sample.json
OPCDataTransfer/Loader/ClickHouseQueries.py
OPCDataTransfer/Loader/Loader.py
OPCDataTransfer/Loader/__init__.py
OPCDataTransfer/OPC/OPC.py
OPCDataTransfer/OPC/__init__.py
OPCDataTransfer/ServiceFunctions/Enumerators.py
OPCDataTransfer/ServiceFunctions/Parser.py
OPCDataTransfer/ServiceFunctions/__init__.py
OPCDataTransfer/Simulation/Simulation.py
OPCDataTransfer/Simulation/WrightToOPC.py
OPCDataTransfer/Simulation/__init__.py
OPCDataTransfer/Visualization/ArrayFunctions.py
OPCDataTransfer/Visualization/DataVisualization.py
OPCDataTransfer/Visualization/__init__.py