Metadata-Version: 2.1
Name: OPCDataTransfer
Version: 1.1.1
Summary: Python ETL script for reading data from OPC-server
Home-page: https://github.com/Shanginre/OPCDataTransfer
Author: Roman Shangin
Author-email: shanginre@gmail.com
License: UNKNOWN
Platform: UNKNOWN
Classifier: Programming Language :: Python :: 3
Classifier: License :: OSI Approved :: MIT License
Classifier: Operating System :: Microsoft :: Windows
Requires-Python: >=3.6-32
